views_stepshift/__init__.py
views_stepshift/api.py
views_stepshift/calibration.py
views_stepshift/config.py
views_stepshift/data_selector.py
views_stepshift/datautils.py
views_stepshift/ebma.py
views_stepshift/evallib.py
views_stepshift/miscutils.py
views_stepshift/statsutils.py
views_stepshift/translib.py
views_stepshift-0.2.1.dist-info/WHEEL
views_stepshift-0.2.1.dist-info/METADATA
views_stepshift-0.2.1.dist-info/RECORD
