Metadata-Version: 2.1
Name: views-stepshift
Version: 0.2.1
Summary: The code used to run modelling pipelines at ViEWS
License: MIT
Author: Frederick Hoyles
Requires-Python: >=3.8,<4.0
Classifier: License :: OSI Approved :: MIT License
Classifier: Programming Language :: Python :: 3
Classifier: Programming Language :: Python :: 3.8
Classifier: Programming Language :: Python :: 3.9
Requires-Dist: joblib (>=1.0.1,<2.0.0)
Requires-Dist: pandas (>=1.2.4,<2.0.0)
Requires-Dist: scikit-learn (>=0.24.2,<0.25.0)
Requires-Dist: statsmodels (>=0.12.2,<0.13.0)
Requires-Dist: toolz (>=0.11.1,<0.12.0)
